<annotation><folder>fireSmoke</folder><filename>0.jpg</filename><path>/home/hardik/workspace/fire&amp;smoke/fireSmoke/images/0.jpg</path><source><database>Unknown</database></source><size><width>640</width><height>463</height><depth>3</depth></size><segmented>0</segmented><object><name>Smoke</name><pose>Unspecified</pose><truncated>0</truncated><difficult>0</difficult><bndbox><xmin>184</xmin><xmax>274</xmax><ymin>38</ymin><ymax>95</ymax></bndbox></object><object><name>Fire</name><pose>Unspecified</pose><truncated>0</truncated><difficult>0</difficult><bndbox><xmin>110</xmin><xmax>291</xmax><ymin>138</ymin><ymax>324</ymax></bndbox></object></annotation>